hasiicommon/__init__.py
hasiicommon/py.typed
hasiicommon/resources/__init__.py
hasiicommon/resources/py.typed
hasiicommon/resources/images/DefaultPreferences.py
hasiicommon/resources/images/__init__.py
hasiicommon/resources/images/py.typed
hasiicommon/resources/images/icons/__init__.py
hasiicommon/resources/images/icons/embedded16/ImgToolboxActor.py
hasiicommon/resources/images/icons/embedded16/ImgToolboxArrow.py
hasiicommon/resources/images/icons/embedded16/ImgToolboxClass.py
hasiicommon/resources/images/icons/embedded16/ImgToolboxNewClassDiagram.py
hasiicommon/resources/images/icons/embedded16/ImgToolboxNewProject.py
hasiicommon/resources/images/icons/embedded16/ImgToolboxNewSequenceDiagram.py
hasiicommon/resources/images/icons/embedded16/ImgToolboxNewUseCaseDiagram.py
hasiicommon/resources/images/icons/embedded16/ImgToolboxNote.py
hasiicommon/resources/images/icons/embedded16/ImgToolboxOpenFile.py
hasiicommon/resources/images/icons/embedded16/ImgToolboxRedo.py
hasiicommon/resources/images/icons/embedded16/ImgToolboxRelationshipAggregation.py
hasiicommon/resources/images/icons/embedded16/ImgToolboxRelationshipAssociation.py
hasiicommon/resources/images/icons/embedded16/ImgToolboxRelationshipComposition.py
hasiicommon/resources/images/icons/embedded16/ImgToolboxRelationshipInheritance.py
hasiicommon/resources/images/icons/embedded16/ImgToolboxRelationshipNote.py
hasiicommon/resources/images/icons/embedded16/ImgToolboxRelationshipRealization.py
hasiicommon/resources/images/icons/embedded16/ImgToolboxSaveDiagram.py
hasiicommon/resources/images/icons/embedded16/ImgToolboxSequenceDiagramInstance.py
hasiicommon/resources/images/icons/embedded16/ImgToolboxSequenceDiagramMessage.py
hasiicommon/resources/images/icons/embedded16/ImgToolboxText.py
hasiicommon/resources/images/icons/embedded16/ImgToolboxUndo.py
hasiicommon/resources/images/icons/embedded16/ImgToolboxUseCase.py
hasiicommon/resources/images/icons/embedded16/ImgToolboxZoomIn.py
hasiicommon-0.3.1.dist-info/LICENSE
hasiicommon-0.3.1.dist-info/METADATA
hasiicommon-0.3.1.dist-info/WHEEL
hasiicommon-0.3.1.dist-info/top_level.txt
hasiicommon-0.3.1.dist-info/RECORD
