Metadata-Version: 2.1
Name: hasiicommon
Version: 0.3.1
Summary: Humberto`s Common Stuff
Home-page: https://github.com/hasii2011/hasiicommon
Author: Humberto A. Sanchez II
Author-email: Humberto.A.Sanchez.II@gmail.com
Maintainer: Humberto A. Sanchez II
Maintainer-email: humberto.a.sanchez.ii@gmail.com
License-File: LICENSE
Requires-Dist: hasiihelper (==0.2.1)
Requires-Dist: Deprecated (~=1.2.14)
Requires-Dist: wxPython (~=4.2.1)
